MANIFEST.in
setup.py
pyfpstool/__init__.py
pyfpstool/__main__.py
pyfpstool/byfpsmeter
pyfpstool/draw.py
pyfpstool/logconv.py
pyfpstool/rdlog.py
pyfpstool/rotate.py
pyfpstool.egg-info/PKG-INFO
pyfpstool.egg-info/SOURCES.txt
pyfpstool.egg-info/dependency_links.txt
pyfpstool.egg-info/entry_points.txt
pyfpstool.egg-info/requires.txt
pyfpstool.egg-info/top_level.txt
pyfpstool/androaxml/__init__.py
pyfpstool/androaxml/androguard.zip