Metadata-Version: 1.0
Name: pyfpstool
Version: 0.7
Summary: get fps rate tool
Home-page: http://github.com/netease/unknown
Author: codeskyblue
Author-email: codeskyblue@gmail.com
License: MIT
Platform: UNKNOWN
